transport/__init__.py
transport/transport.py
transportchb-0.0.1.dist-info/LICENSE
transportchb-0.0.1.dist-info/METADATA
transportchb-0.0.1.dist-info/WHEEL
transportchb-0.0.1.dist-info/top_level.txt
transportchb-0.0.1.dist-info/RECORD
