Metadata-Version: 2.1
Name: transportchb
Version: 0.0.1
Summary: Couchbase Migration module
Home-page: https://github.com/emrecilekci19/transportc
Author: Emre Çilekci
Author-email: huseyin.d3r@gmail.com
Project-URL: Bug Tracker, https://github.com/emrecilekci19/transportc
Classifier: Programming Language :: Python :: 3
Classifier: License :: OSI Approved :: MIT License
Classifier: Operating System :: OS Independent
Requires-Python: >=3.6
License-File: LICENSE
Requires-Dist: tabulate
